et_micc_tools/__init__.py
et_micc_tools/logging_tools.py
et_micc_tools/static_vars.py
et_micc_tools/stopwatch.py
et_micc_tools/tomlfile.py
et_micc_tools/utils.py
et_micc_tools-0.1.2.dist-info/entry_points.txt
et_micc_tools-0.1.2.dist-info/LICENSE
et_micc_tools-0.1.2.dist-info/WHEEL
et_micc_tools-0.1.2.dist-info/METADATA
et_micc_tools-0.1.2.dist-info/RECORD
